rock/main.py
rockanalysis/__init__.py
rockanalysis/main.py
rockanalysis-1.0.0.dist-info/LICENSE
rockanalysis-1.0.0.dist-info/METADATA
rockanalysis-1.0.0.dist-info/WHEEL
rockanalysis-1.0.0.dist-info/top_level.txt
rockanalysis-1.0.0.dist-info/RECORD
