Metadata-Version: 2.1
Name: rockanalysis
Version: 1.0.0
Summary: ROCK Data Analysis Package
Home-page: https://github.com/bweindorf/rockanalysis.git
Author: Brandon Weindorf
Author-email: bjweindorf@gmail.com
License: UNKNOWN
Platform: UNKNOWN
Classifier: Programming Language :: Python :: 3
Classifier: License :: OSI Approved :: MIT License
Classifier: Operating System :: OS Independent
Requires-Python: >=3.6
Requires-Dist: matplotlib
